qaviton_io/__init__.py
qaviton_io/async_manager.py
qaviton_io/logger.py
qaviton_io/process_manager.py
qaviton_io/types.py
qaviton_io/utils/__init__.py
qaviton_io/utils/log.py
qaviton_io-2019.11.13.13.29.23.745334.dist-info/LICENSE
qaviton_io-2019.11.13.13.29.23.745334.dist-info/METADATA
qaviton_io-2019.11.13.13.29.23.745334.dist-info/WHEEL
qaviton_io-2019.11.13.13.29.23.745334.dist-info/top_level.txt
qaviton_io-2019.11.13.13.29.23.745334.dist-info/RECORD
