Metadata-Version: 2.1
Name: qaviton-io
Version: 2019.11.13.13.29.23.745334
Summary: qaviton io
Home-page: https://github.com/yehonadav/qaviton_io
Author: yehonadav
Author-email: qaviton@gmail.com
License: apache-2.0
Platform: UNKNOWN
Classifier: Programming Language :: Python :: 3.7
Requires-Dist: qaviton-processes (>=2019.11.1.13.50.43.917059)
Requires-Dist: colorama (>=0.4.1)
